{"file:///C:/Users/Eric/Documents/Mobi":{"assets/images/hashes.json":"8nXUI0sUIVRN1+5zmFRltQ==","assets/images/icon.svg":"3yvepB8J/TowioJ8mepmdw==","assets/images/fullstack-4.svg":"wMtFnW4JRNXwO+HIl+RZ1g==","assets/images/ui-4.svg":"1vcXdszGZsSohzNyIDewfQ==","assets/images/data-4.svg":"1xWr+QH24i/ssdqf5O8JMw==","assets/images/mobile-2.svg":"wOr2SMlewwKmdgzXE0r9XQ==","assets/images/lara-vue-1.svg":"ezlO42CkaW3yrVIWv6az1g==","assets/images/api-1.svg":"BK4stzBkLkCIclXjBewcFg==","assets/images/wordpress-1.svg":"asd4C+OjkCAjEc9woPpJDQ==","assets/images/ai-machine.svg":"UwSCufj/36wCoVGcBvRMuw==","assets/images/java-9.svg":"NB1XTxy2IwnbxqsDGLRLXg==","assets/images/hacking-1.svg":"NZ25XW/X7W0WU2z7SmIqOw==","assets/images/analysisdesign-2.svg":"TSony6Be8szDeCY1Mudx2g==","assets/images/testautomation-1.svg":"lxGynaZdhc9mhQGpwBsBtg==","assets/images/sea-1.svg":"IGcIENOUP9L7iNT5KgI1lg==","assets/images/scrum-1.svg":"h5YikJjCYfYtfsgL1tp4wg==","assets/images/python-5.svg":"GfDEe6+nCq+zpNSwpvmvUQ==","assets/images/custom-2.svg":"cakmOwjCz/+53q1GlGMXAg==","assets/images/4380747.jpg":"xZ/UHtLJEylcarAqcCaWoA==","assets/images/movileapp.svg":"OQYa5J8GanusTeaoYFl6yA==","assets/images/assessment.svg":"FsSuP89Cx2chQHsGLzYJZg==","assets/images/ui-ux-4.svg":"azP3kljmgjXOn6dWMauGfQ==","assets/images/clients1.svg":"LyVPRrQlkKYDYpk56Xw3XQ==","assets/images/dp-2.png":"susnxneJi3MWkfIbu6fSwg==","assets/images/dp2-1.png":"vf699yNGNUzJrdfLStcs0g==","assets/images/icon-w-name-2.svg":"Ko25GccEA+yxp18cRzUerA==","assets/images/full-stack-4.svg":"QqjZZdQbSuMNw4udiIaBkQ==","assets/images/ui-3.svg":"wanQupAytvEj43sQ77adRg==","assets/images/vue-2.svg":"HSklzcmqF09XddRxkmOLIQ==","assets/images/data-2.svg":"OEeBqbvRhO3tdJN42BS1FA==","assets/images/softwaretest.svg":"ymV/Ei9wAUe/cNs5a4e7Vg==","assets/images/wordpress-2.svg":"daolzYCYC1Rti2iD2X1ghw==","assets/images/mobile.svg":"vTnrJdoJDNhoGz4nreAnyg==","assets/images/ai.svg":"PpcmxhLkIimT+/tsfUbbrw==","assets/images/java-10.svg":"KcyYWCihVSzxMAwrIYAWgw==","assets/images/hacking-3.svg":"FzEmdtKg+Gr+3nWifI7vzg==","assets/images/analysisdesign-1.svg":"Pn7Cb3SGrGypGs3LcDq9Gg==","assets/images/testautomation.svg":"q7AtqMU0zYK6/cuHqYhVBQ==","assets/images/sea.svg":"MiG4KnUQFd+4bIS8ymdDNg==","assets/images/scrum.svg":"KtUCns29U1VoFjeP0jTSBg==","assets/images/dp3.png":"afJ3WUZhNW4yAE6mFsTipg==","assets/images/dp4.png":"04nlsM51Wk7uZF2G+ymn0g==","assets/images/python-4.svg":"pJZ55KH0sjphf2PPiOXSKQ==","assets/images/custom-1.svg":"SyBPbKrGO+7kyzs+PQ9aBw==","assets/images/bg.svg":"R+THQXPUjKBHl5vUb8JWBg==","assets/bootstrap/css/bootstrap.min.css":"qGiBfMEZYUPQ8GJUeqipZw==","assets/bootstrap/css/bootstrap-grid.min.css":"4bnuDDTauYpkcZNhkYKtrg==","assets/bootstrap/css/bootstrap-reboot.min.css":"/iLrQLzPIC+HbKPQfUweBg==","assets/bootstrap/js/bootstrap.bundle.min.js":"4jB/FPBUKrTUyehEkinqIg==","assets/smoothscroll/smooth-scroll.js":"I6Cnt5FZXvE7AwxKBjLHIw==","assets/theme/css/style.css":"zwvoPTBYU/IAfgCqrVEA6Q==-VITbTf54ezV7Z7I/e4lZVw==","assets/ytplayer/index.js":"mFY4BIBrp1+/1GbYKiwChg==","assets/parallax/jarallax.js":"dK+LQKyoapkDnRGMTh9jhQ==","assets/parallax/jarallax.css":"2Tta/DdBrdXNDixBji4u9A==","assets/embla/embla.min.js":"+JN5fpraKrFLOFyg8FtNTg==","assets/embla/script.js":"4Ux7F4PHmWed/ig6tpNw0A==","assets/web/assets/mobirise-icons2/mobirise2.css":"+RO7OxVtE1FsD/N7V3/ADw==","assets/web/assets/mobirise-icons2/mobirise2.eot":"B2EjryGRojlTpzr1GHt3LQ==","assets/web/assets/mobirise-icons2/mobirise2.svg":"usCYAy7QdzckfeGReb9wWQ==","assets/web/assets/mobirise-icons2/mobirise2.ttf":"VMdAr7YYQ2ab9KiUyabAGA==","assets/web/assets/mobirise-icons2/mobirise2.woff":"xY3InaTfYGp0nlCuQBMudQ==","assets/dropdown/css/style.css":"Vb8nb3PvfIj5jIp56aQkiA==","assets/dropdown/js/navbar-dropdown.js":"eR+jFVL8KABJEAcdSC/rjQ==","assets/socicon/css/styles.css":"yjHs7tV2SewoW36KZ0bi9w==","assets/socicon/fonts/socicon.eot":"MvYQV8XxgngrhGqjN3oHBw==","assets/socicon/fonts/socicon.svg":"U1iRKoyNjKeR+mUJr3QbXg==","assets/socicon/fonts/socicon.ttf":"IyAo3XNB2a/Q0ml3ZraPsQ==","assets/socicon/fonts/socicon.woff":"zQDjXd6bBUQi87pRsBWVqQ==","assets/socicon/fonts/socicon.woff2":"o3w8h99EHOwP99NXAoHpOQ==","assets/formoid/formoid.min.js":"WTdAU6BjuKe3AU4yIlVc1w==","assets/images/icon-w-name.svg":"WwRBmn03zaVdUvKo/GmRAw==","assets/images/index-meta.svg":"WwRBmn03zaVdUvKo/GmRAw==","assets/images/enroll-meta.svg":"WwRBmn03zaVdUvKo/GmRAw==","assets/images/sponsorships-meta.svg":"WwRBmn03zaVdUvKo/GmRAw==","assets/images/hire-dev-meta.svg":"WwRBmn03zaVdUvKo/GmRAw==","assets/images/courses-meta.svg":"WwRBmn03zaVdUvKo/GmRAw=="},"file:///C:/Users/Eric/Documents/GitHub/zyberlab-test":{"assets/images/hashes.json":"8nXUI0sUIVRN1+5zmFRltQ==","assets/images/icon.svg":"3yvepB8J/TowioJ8mepmdw==","assets/images/fullstack-4.svg":"wMtFnW4JRNXwO+HIl+RZ1g==","assets/images/ui-4.svg":"1vcXdszGZsSohzNyIDewfQ==","assets/images/data-4.svg":"1xWr+QH24i/ssdqf5O8JMw==","assets/images/mobile-2.svg":"wOr2SMlewwKmdgzXE0r9XQ==","assets/images/lara-vue-1.svg":"ezlO42CkaW3yrVIWv6az1g==","assets/images/api-1.svg":"BK4stzBkLkCIclXjBewcFg==","assets/images/wordpress-1.svg":"asd4C+OjkCAjEc9woPpJDQ==","assets/images/ai-machine.svg":"UwSCufj/36wCoVGcBvRMuw==","assets/images/java-9.svg":"NB1XTxy2IwnbxqsDGLRLXg==","assets/images/hacking-1.svg":"NZ25XW/X7W0WU2z7SmIqOw==","assets/images/analysisdesign-2.svg":"TSony6Be8szDeCY1Mudx2g==","assets/images/testautomation-1.svg":"lxGynaZdhc9mhQGpwBsBtg==","assets/images/sea-1.svg":"IGcIENOUP9L7iNT5KgI1lg==","assets/images/scrum-1.svg":"h5YikJjCYfYtfsgL1tp4wg==","assets/images/python-5.svg":"GfDEe6+nCq+zpNSwpvmvUQ==","assets/images/custom-2.svg":"cakmOwjCz/+53q1GlGMXAg==","assets/images/4380747.jpg":"xZ/UHtLJEylcarAqcCaWoA==","assets/images/movileapp.svg":"OQYa5J8GanusTeaoYFl6yA==","assets/images/assessment.svg":"FsSuP89Cx2chQHsGLzYJZg==","assets/images/ui-ux-4.svg":"azP3kljmgjXOn6dWMauGfQ==","assets/images/clients1.svg":"LyVPRrQlkKYDYpk56Xw3XQ==","assets/images/dp-2.png":"susnxneJi3MWkfIbu6fSwg==","assets/images/dp2-1.png":"vf699yNGNUzJrdfLStcs0g==","assets/images/icon-w-name-2.svg":"Ko25GccEA+yxp18cRzUerA==","assets/images/full-stack-4.svg":"QqjZZdQbSuMNw4udiIaBkQ==","assets/images/ui-3.svg":"wanQupAytvEj43sQ77adRg==","assets/images/vue-2.svg":"HSklzcmqF09XddRxkmOLIQ==","assets/images/data-2.svg":"OEeBqbvRhO3tdJN42BS1FA==","assets/images/softwaretest.svg":"ymV/Ei9wAUe/cNs5a4e7Vg==","assets/images/wordpress-2.svg":"daolzYCYC1Rti2iD2X1ghw==","assets/images/mobile.svg":"vTnrJdoJDNhoGz4nreAnyg==","assets/images/ai.svg":"PpcmxhLkIimT+/tsfUbbrw==","assets/images/java-10.svg":"KcyYWCihVSzxMAwrIYAWgw==","assets/images/hacking-3.svg":"FzEmdtKg+Gr+3nWifI7vzg==","assets/images/analysisdesign-1.svg":"Pn7Cb3SGrGypGs3LcDq9Gg==","assets/images/testautomation.svg":"q7AtqMU0zYK6/cuHqYhVBQ==","assets/images/sea.svg":"MiG4KnUQFd+4bIS8ymdDNg==","assets/images/scrum.svg":"KtUCns29U1VoFjeP0jTSBg==","assets/images/dp3.png":"afJ3WUZhNW4yAE6mFsTipg==","assets/images/dp4.png":"04nlsM51Wk7uZF2G+ymn0g==","assets/images/python-4.svg":"pJZ55KH0sjphf2PPiOXSKQ==","assets/images/custom-1.svg":"SyBPbKrGO+7kyzs+PQ9aBw==","assets/images/bg.svg":"R+THQXPUjKBHl5vUb8JWBg==","assets/bootstrap/css/bootstrap.min.css":"qGiBfMEZYUPQ8GJUeqipZw==","assets/bootstrap/css/bootstrap-grid.min.css":"4bnuDDTauYpkcZNhkYKtrg==","assets/bootstrap/css/bootstrap-reboot.min.css":"/iLrQLzPIC+HbKPQfUweBg==","assets/bootstrap/js/bootstrap.bundle.min.js":"4jB/FPBUKrTUyehEkinqIg==","assets/smoothscroll/smooth-scroll.js":"I6Cnt5FZXvE7AwxKBjLHIw==","assets/theme/css/style.css":"zwvoPTBYU/IAfgCqrVEA6Q==-VITbTf54ezV7Z7I/e4lZVw==","assets/ytplayer/index.js":"mFY4BIBrp1+/1GbYKiwChg==","assets/parallax/jarallax.js":"dK+LQKyoapkDnRGMTh9jhQ==","assets/parallax/jarallax.css":"2Tta/DdBrdXNDixBji4u9A==","assets/embla/embla.min.js":"+JN5fpraKrFLOFyg8FtNTg==","assets/embla/script.js":"4Ux7F4PHmWed/ig6tpNw0A==","assets/web/assets/mobirise-icons2/mobirise2.css":"+RO7OxVtE1FsD/N7V3/ADw==","assets/web/assets/mobirise-icons2/mobirise2.eot":"B2EjryGRojlTpzr1GHt3LQ==","assets/web/assets/mobirise-icons2/mobirise2.svg":"usCYAy7QdzckfeGReb9wWQ==","assets/web/assets/mobirise-icons2/mobirise2.ttf":"VMdAr7YYQ2ab9KiUyabAGA==","assets/web/assets/mobirise-icons2/mobirise2.woff":"xY3InaTfYGp0nlCuQBMudQ==","assets/dropdown/css/style.css":"Vb8nb3PvfIj5jIp56aQkiA==","assets/dropdown/js/navbar-dropdown.js":"eR+jFVL8KABJEAcdSC/rjQ==","assets/socicon/css/styles.css":"yjHs7tV2SewoW36KZ0bi9w==","assets/socicon/fonts/socicon.eot":"MvYQV8XxgngrhGqjN3oHBw==","assets/socicon/fonts/socicon.svg":"U1iRKoyNjKeR+mUJr3QbXg==","assets/socicon/fonts/socicon.ttf":"IyAo3XNB2a/Q0ml3ZraPsQ==","assets/socicon/fonts/socicon.woff":"zQDjXd6bBUQi87pRsBWVqQ==","assets/socicon/fonts/socicon.woff2":"o3w8h99EHOwP99NXAoHpOQ==","assets/formoid/formoid.min.js":"WTdAU6BjuKe3AU4yIlVc1w==","assets/images/icon-w-name.svg":"WwRBmn03zaVdUvKo/GmRAw==","assets/images/index-meta.svg":"WwRBmn03zaVdUvKo/GmRAw==","assets/images/enroll-meta.svg":"WwRBmn03zaVdUvKo/GmRAw==","assets/images/sponsorships-meta.svg":"WwRBmn03zaVdUvKo/GmRAw==","assets/images/hire-dev-meta.svg":"WwRBmn03zaVdUvKo/GmRAw==","assets/images/courses-meta.svg":"WwRBmn03zaVdUvKo/GmRAw=="}}